topsis/__init__.py
topsis/algo.py
topsis/main.py
topsis_Angad_Singh_102217132-0.0.3.dist-info/LICENSE
topsis_Angad_Singh_102217132-0.0.3.dist-info/METADATA
topsis_Angad_Singh_102217132-0.0.3.dist-info/WHEEL
topsis_Angad_Singh_102217132-0.0.3.dist-info/top_level.txt
topsis_Angad_Singh_102217132-0.0.3.dist-info/RECORD
