Metadata-Version: 2.1
Name: topsis-Angad-Singh-102217132
Version: 0.0.3
Author: Angad Singh
Author-email: asingh36_be22@thapar.edu 
License: MIT
License-File: LICENSE
Requires-Dist: pandas
Requires-Dist: numpy
